[
  {
    "id": "N24",
    "name_th": "คูคต",
    "name_en": "Khu Khot",
    "type": 1,
    "type_name": "สายสีเขียวสุขุมวิท",
    "have_parking": 0,
    "lat": 13.932338847782251,
    "long": 100.64660335031027,
    "exit_doors": [
      {
        "id": 1,
        "exit_name": "ทางออก 1",
        "lat": 13.9325431564207,
        "long": 100.64599853272117
      },
      {
        "id": 2,
        "exit_name": "ทางออก 2",
        "lat": 13.93220609274974,
        "long": 100.64595770842676
      },
      {
        "id": 3,
        "exit_name": "ทางออก 3",
        "lat": 13.9324356732471,
        "long": 100.64727694382869
      },
      {
        "id": 4,
        "exit_name": "ทางออก 4",
        "lat": 13.932178095112743,
        "long": 100.6472673284107
      }
    ]
  },
  {
    "id": "N23",
    "name_th": "แยก คปอ.",
    "name_en": "Yaek Kor Por Aor",
    "type": 1,
    "type_name": "สายสีเขียวสุขุมวิท",
    "have_parking": 0,
    "lat": 13.92606441,
    "long": 100.6266272,
    "exit_doors": [
      {
        "id": 1,
        "exit_name": "ทางออก 1",
        "lat": 13.924745935972252,
        "long": 100.62560540731263
      },
      {
        "id": 2,
        "exit_name": "ทางออก 2",
        "lat": 13.924634287870632,
        "long": 100.62585801882352
      },
      {
        "id": 3,
        "exit_name": "ทางออก 3",
        "lat": 13.925749397915794,
        "long": 100.62581837630945
      },
      {
        "id": 4,
        "exit_name": "ทางออก 4",
        "lat": 13.925212562119784,
        "long": 100.62624161146395
      }
    ]
  },
  {
    "id": "N22",
    "name_th": "พิพิธภัณฑ์กองทัพอากาศ",
    "name_en": "Royal Thai Air Force Museum",
    "type": 1,
    "type_name": "สายสีเขียวสุขุมวิท",
    "have_parking": 0,
    "lat": 13.91794958,
    "long": 100.621695,
    "exit_doors": [
      {
        "id": 1,
        "exit_name": "ทางออก 1",
        "lat": 13.917525656398139,
        "long": 100.62133389620725
      },
      {
        "id": 2,
        "exit_name": "ทางออก 2",
        "lat": 13.917405128009394,
        "long": 100.62158360820655
      },
      {
        "id": 3,
        "exit_name": "ทางออก 3",
        "lat": 13.91845412024562,
        "long": 100.62193839031971
      },
      {
        "id": 4,
        "exit_name": "ทางออก 4",
        "lat": 13.918322996478118,
        "long": 100.62215125956502
      }
    ]
  },
  {
    "id": "N21",
    "name_th": "โรงพยาบาลภูมิพลอดุลยเดช",
    "name_en": "Bhumiphol Adulyadej Hospital",
    "type": 1,
    "type_name": "สายสีเขียวสุขุมวิท",
    "have_parking": 0,
    "lat": 13.91076172,
    "long": 100.6174338,
    "exit_doors": [
      {
        "id": 1,
        "exit_name": "ทางออก 1",
        "lat": 13.910239822513441,
        "long": 100.61703161809875
      },
      {
        "id": 2,
        "exit_name": "ทางออก 2",
        "lat": 13.910100018065146,
        "long": 100.6173084515994
      },
      {
        "id": 3,
        "exit_name": "ทางออก 3",
        "lat": 13.911276551574002,
        "long": 100.6176414000089
      },
      {
        "id": 4,
        "exit_name": "ทางออก 4",
        "lat": 13.911100435057781,
        "long": 100.61786585961569
      }
    ]
  },
  {
    "id": "N20",
    "name_th": "สะพานใหม่",
    "name_en": "Saphan Mai",
    "type": 1,
    "type_name": "สายสีเขียวสุขุมวิท",
    "have_parking": 0,
    "lat": 13.89660065,
    "long": 100.609124,
    "exit_doors": [
      {
        "id": 1,
        "exit_name": "ทางออก 1",
        "lat": 13.89613853031296,
        "long": 100.60873948706848
      },
      {
        "id": 2,
        "exit_name": "ทางออก 2",
        "lat": 13.895992341137488,
        "long": 100.60895371212813
      },
      {
        "id": 3,
        "exit_name": "ทางออก 3",
        "lat": 13.897141309801063,
        "long": 13.897141309801063
      },
      {
        "id": 4,
        "exit_name": "ทางออก 4",
        "lat": 13.896997232739643,
        "long": 100.60953732416331
      }
    ]
  },
  {
    "id": "N19",
    "name_th": "สายหยุด",
    "name_en": "Sai Yud",
    "type": 1,
    "type_name": "สายสีเขียวสุขุมวิท",
    "have_parking": 0,
    "lat": 13.88838617,
    "long": 100.6044369,
    "exit_doors": [
      {
        "id": 1,
        "exit_name": "ทางออก 1",
        "lat": 13.887991068102615,
        "long": 100.60400567607977
      },
      {
        "id": 2,
        "exit_name": "ทางออก 2",
        "lat": 13.887808585510431,
        "long": 100.60412590186617
      },
      {
        "id": 3,
        "exit_name": "ทางออก 3",
        "lat": 13.88896876903962,
        "long": 100.60458608460168
      },
      {
        "id": 4,
        "exit_name": "ทางออก 4",
        "lat": 13.88887418300294,
        "long": 100.60477809535179
      }
    ]
  },
  {
    "id": "N18",
    "name_th": "พหลโยธิน 59",
    "name_en": "Phahol Yothin 59",
    "type": 1,
    "type_name": "สายสีเขียวสุขุมวิท",
    "have_parking": 0,
    "lat": 13.88245547882835,
    "long": 100.60076585118547,
    "exit_doors": [
      {
        "id": 1,
        "exit_name": "ทางออก 1",
        "lat": 13.881942612032711,
        "long": 100.60043870063438
      },
      {
        "id": 2,
        "exit_name": "ทางออก 2",
        "lat": 13.882001266126279,
        "long": 100.60068826773053
      },
      {
        "id": 3,
        "exit_name": "ทางออก 3",
        "lat": 13.88293822560575,
        "long": 100.60101988168246
      },
      {
        "id": 4,
        "exit_name": "ทางออก 4",
        "lat": 13.882809962267933,
        "long": 100.60117403364038
      }
    ]
  },
  {
    "id": "N17",
    "name_th": "วัดพระศรีมหาธาตุ",
    "name_en": "Wat Phra Si Maha That",
    "type": 1,
    "type_name": "สายสีเขียวสุขุมวิท",
    "have_parking": 0,
    "lat": 13.87519066,
    "long": 100.5961231,
    "exit_doors": [
      {
        "id": 1,
        "exit_name": "ทางออก 1",
        "lat": 13.875062383144027,
        "long": 100.59651747290853
      },
      {
        "id": 2,
        "exit_name": "ทางออก 2",
        "lat": 13.874549276170994,
        "long": 100.5966118533472
      },
      {
        "id": 3,
        "exit_name": "ทางออก 3",
        "lat": 13.87664908826289,
        "long": 100.59705804476107
      },
      {
        "id": 4,
        "exit_name": "ทางออก 4",
        "lat": 13.876195414232349,
        "long": 100.59772236501097
      }
    ]
  },
  {
    "id": "N16",
    "name_th": "กรมทหารราบที่ 11",
    "name_en": "11 St Infantry Regiment",
    "type": 1,
    "type_name": "สายสีเขียวสุขุมวิท",
    "have_parking": 0,
    "lat": 13.86752947,
    "long": 100.5919394,
    "exit_doors": [
      {
        "id": 1,
        "exit_name": "ทางออก 1",
        "lat": 13.867296440644271,
        "long": 100.5917572895858
      },
      {
        "id": 2,
        "exit_name": "ทางออก 2",
        "lat": 13.866978604550969,
        "long": 100.59183027504797
      },
      {
        "id": 3,
        "exit_name": "ทางออก 3",
        "lat": 13.868099348693676,
        "long": 100.59229174702831
      },
      {
        "id": 4,
        "exit_name": "ทางออก 4",
        "lat": 13.86800095785042,
        "long": 100.5924727862239
      }
    ]
  },
  {
    "id": "N15",
    "name_th": "บางบัว",
    "name_en": "Bang Bua",
    "type": 1,
    "type_name": "สายสีเขียวสุขุมวิท",
    "have_parking": 0,
    "lat": 13.85599836,
    "long": 100.5851736,
    "exit_doors": [
      {
        "id": 1,
        "exit_name": "ทางออก 1",
        "lat": 13.855560867218973,
        "long": 100.58490524632518
      },
      {
        "id": 2,
        "exit_name": "ทางออก 2",
        "lat": 13.85558231970996,
        "long": 100.58515591471489
      },
      {
        "id": 3,
        "exit_name": "ทางออก 3",
        "lat": 13.856575760011255,
        "long": 100.58550055098688
      },
      {
        "id": 4,
        "exit_name": "ทางออก 4",
        "lat": 13.856400959961745,
        "long": 100.58561974842226
      }
    ]
  },
  {
    "id": "N14",
    "name_th": "กรมป่าไม้",
    "name_en": "Royal Forest Department",
    "type": 1,
    "type_name": "สายสีเขียวสุขุมวิท",
    "have_parking": 0,
    "lat": 13.85036596,
    "long": 100.5818304,
    "exit_doors": [
      {
        "id": 1,
        "exit_name": "ทางออก 1",
        "lat": 13.849882882753205,
        "long": 100.58148649926645
      },
      {
        "id": 2,
        "exit_name": "ทางออก 2",
        "lat": 13.849738376593875,
        "long": 100.58172585143922
      },
      {
        "id": 3,
        "exit_name": "ทางออก 3",
        "lat": 13.850807684603701,
        "long": 100.58211630068989
      },
      {
        "id": 4,
        "exit_name": "ทางออก 4",
        "lat": 13.850537275290677,
        "long": 100.58219218012344
      }
    ]
  },
  {
    "id": "N13",
    "name_th": "มหาวิทยาลัยเกษตรศาสตร์",
    "name_en": "Kasetsart University",
    "type": 1,
    "type_name": "สายสีเขียวสุขุมวิท",
    "have_parking": 0,
    "lat": 13.84236056,
    "long": 100.5770899,
    "exit_doors": [
      {
        "id": 1,
        "exit_name": "ทางออก 1",
        "lat": 13.841861891848607,
        "long": 100.57674625855161
      },
      {
        "id": 2,
        "exit_name": "ทางออก 2",
        "lat": 13.841661460986135,
        "long": 100.5769480110903
      },
      {
        "id": 3,
        "exit_name": "ทางออก 3",
        "lat": 13.843035921615506,
        "long": 100.57749372307352
      },
      {
        "id": 4,
        "exit_name": "ทางออก 4",
        "lat": 13.842717148793957,
        "long": 100.57758946043243
      }
    ]
  },
  {
    "id": "N12",
    "name_th": "เสนานิคม",
    "name_en": "Sena Nikhom",
    "type": 1,
    "type_name": "สายสีเขียวสุขุมวิท",
    "have_parking": 0,
    "lat": 13.83636145,
    "long": 100.5736125,
    "exit_doors": [
      {
        "id": 1,
        "exit_name": "ทางออก 1",
        "lat": 13.836028382598935,
        "long": 100.57330944906329
      },
      {
        "id": 2,
        "exit_name": "ทางออก 2",
        "lat": 13.83590303051609,
        "long": 100.57346169565592
      },
      {
        "id": 3,
        "exit_name": "ทางออก 3",
        "lat": 13.83693920988234,
        "long": 100.57383031282549
      },
      {
        "id": 4,
        "exit_name": "ทางออก 4",
        "lat": 13.836693427784464,
        "long": 100.57393231887424
      }
    ]
  },
  {
    "id": "N11",
    "name_th": "รัชโยธิน",
    "name_en": "Ratchayothin",
    "type": 1,
    "type_name": "สายสีเขียวสุขุมวิท",
    "have_parking": 0,
    "lat": 13.83086081,
    "long": 100.5702733,
    "exit_doors": [
      {
        "id": 1,
        "exit_name": "ทางออก 1",
        "lat": 13.829223948065039,
        "long": 100.56921436999745
      },
      {
        "id": 2,
        "exit_name": "ทางออก 2",
        "lat": 13.82930242024394,
        "long": 100.56957968323334
      },
      {
        "id": 3,
        "exit_name": "ทางออก 3",
        "lat": 13.830391977054017,
        "long": 100.56994173060178
      },
      {
        "id": 4,
        "exit_name": "ทางออก 4",
        "lat": 13.830207911581422,
        "long": 100.57009581444713
      }
    ]
  },
  {
    "id": "N10",
    "name_th": "พหลโยธิน 24",
    "name_en": "Phahonyothin 24",
    "type": 1,
    "type_name": "สายสีเขียวสุขุมวิท",
    "have_parking": 0,
    "lat": 13.8240331,
    "long": 100.5664669,
    "exit_doors": [
      {
        "id": 1,
        "exit_name": "ทางออก 1",
        "lat": 13.823837851735222,
        "long": 100.56607073395588
      },
      {
        "id": 2,
        "exit_name": "ทางออก 2",
        "lat": 13.823768549461358,
        "long": 100.56631462357646
      },
      {
        "id": 3,
        "exit_name": "ทางออก 3",
        "lat": 13.824690679096287,
        "long": 100.56658952147363
      },
      {
        "id": 4,
        "exit_name": "ทางออก 4",
        "lat": 13.824347270576073,
        "long": 100.56666304282359
      }
    ]
  },
  {
    "id": "N09",
    "name_th": "ห้าแยกลาดพร้าว",
    "name_en": "Ha Yaek Lat Phrao",
    "type": 1,
    "type_name": "สายสีเขียวสุขุมวิท",
    "have_parking": 0,
    "lat": 13.81645083,
    "long": 100.5619551,
    "exit_doors": [
      {
        "id": 1,
        "exit_name": "ทางออก 1",
        "lat": 13.816408014928586,
        "long": 100.56159141215089
      },
      {
        "id": 2,
        "exit_name": "ทางออก 2",
        "lat": 13.816013585809765,
        "long": 100.56177090544976
      },
      {
        "id": 3,
        "exit_name": "ทางออก 3",
        "lat": 13.817109550299765,
        "long": 100.56205361474547
      },
      {
        "id": 4,
        "exit_name": "ทางออก 4",
        "lat": 13.817027325398225,
        "long": 100.56236715961711
      }
    ]
  },
  {
    "id": "N08",
    "name_th": "หมอชิต",
    "name_en": "Mo Chit",
    "type": 1,
    "type_name": "สายสีเขียวสุขุมวิท",
    "have_parking": 0,
    "lat": 13.80263954,
    "long": 100.5538508,
    "exit_doors": [
      {
        "id": 1,
        "exit_name": "ทางออก 1",
        "lat": 13.80240629915024,
        "long": 100.5533242819171
      },
      {
        "id": 2,
        "exit_name": "ทางออก 2",
        "lat": 13.80227506377755,
        "long": 100.55375097108325
      },
      {
        "id": 3,
        "exit_name": "ทางออก 3",
        "lat": 13.803109113312326,
        "long": 100.553744938753
      },
      {
        "id": 4,
        "exit_name": "ทางออก 4",
        "lat": 13.802956055181781,
        "long": 100.55415800399398
      }
    ]
  },
  {
    "id": "N07",
    "name_th": "สะพานควาย",
    "name_en": "Saphan Khwai",
    "type": 1,
    "type_name": "สายสีเขียวสุขุมวิท",
    "have_parking": 0,
    "lat": 13.79356355,
    "long": 100.5496576,
    "exit_doors": [
      {
        "id": 1,
        "exit_name": "ทางออก 1",
        "lat": 13.793182460344939,
        "long": 100.54932855402139
      },
      {
        "id": 2,
        "exit_name": "ทางออก 2",
        "lat": 13.793219521276889,
        "long": 100.54957750242126
      },
      {
        "id": 3,
        "exit_name": "ทางออก 3",
        "lat": 13.794391352287487,
        "long": 100.54979216286847
      },
      {
        "id": 4,
        "exit_name": "ทางออก 4",
        "lat": 13.794186420117079,
        "long": 100.54997052933615
      }
    ]
  },
  {
    "id": "N05",
    "name_th": "อารีย์",
    "name_en": "Ari",
    "type": 1,
    "type_name": "สายสีเขียวสุขุมวิท",
    "have_parking": 0,
    "lat": 13.77969665,
    "long": 100.5446464,
    "exit_doors": [
      {
        "id": 1,
        "exit_name": "ทางออก 1",
        "lat": 13.779428268457282,
        "long": 100.54445365592953
      },
      {
        "id": 2,
        "exit_name": "ทางออก 2",
        "lat": 13.77912320437754,
        "long": 100.5445368392544
      },
      {
        "id": 3,
        "exit_name": "ทางออก 3",
        "lat": 13.780276132785128,
        "long": 100.54472258246558
      },
      {
        "id": 4,
        "exit_name": "ทางออก 4",
        "lat": 13.779892203975313,
        "long": 100.54482288835135
      }
    ]
  },
  {
    "id": "N04",
    "name_th": "สนามเป้า",
    "name_en": "Sanam Pao",
    "type": 1,
    "type_name": "สายสีเขียวสุขุมวิท",
    "have_parking": 0,
    "lat": 13.77233578,
    "long": 100.5421482,
    "exit_doors": [
      {
        "id": 1,
        "exit_name": "ทางออก 1",
        "lat": 13.772112931973712,
        "long": 100.54178775429963
      },
      {
        "id": 2,
        "exit_name": "ทางออก 2",
        "lat": 13.77195641864162,
        "long": 100.54198056543409
      },
      {
        "id": 3,
        "exit_name": "ทางออก 3",
        "lat": 13.773156748303107,
        "long": 100.54214697201661
      },
      {
        "id": 4,
        "exit_name": "ทางออก 4",
        "lat": 13.773159488275807,
        "long": 100.5424038889631
      }
    ]
  },
  {
    "id": "N03",
    "name_th": "อนุสาวรีย์ชัยสมรภูมิ",
    "name_en": "Victory Monument",
    "type": 1,
    "type_name": "สายสีเขียวสุขุมวิท",
    "have_parking": 0,
    "lat": 13.76283455,
    "long": 100.5371079,
    "exit_doors": [
      {
        "id": 1,
        "exit_name": "ทางออก 1",
        "lat": 13.762434868092521,
        "long": 100.53674777128451
      },
      {
        "id": 2,
        "exit_name": "ทางออก 2",
        "lat": 13.762268251451887,
        "long": 100.5369539828084
      },
      {
        "id": 3,
        "exit_name": "ทางออก 3",
        "lat": 13.763113441500467,
        "long": 100.53714560665782
      },
      {
        "id": 4,
        "exit_name": "ทางออก 4",
        "lat": 13.763041262060037,
        "long": 100.53740146331268
      }
    ]
  },
  {
    "id": "N02",
    "name_th": "พญาไท",
    "name_en": "Phaya Thai",
    "type": 1,
    "type_name": "สายสีเขียวสุขุมวิท",
    "have_parking": 0,
    "lat": 13.75652679,
    "long": 100.5337291,
    "exit_doors": [
      {
        "id": 1,
        "exit_name": "ทางออก 1",
        "lat": 13.756464232985664,
        "long": 100.53342333888097
      },
      {
        "id": 2,
        "exit_name": "ทางออก 2",
        "lat": 13.756361324776702,
        "long": 100.53365400885517
      },
      {
        "id": 3,
        "exit_name": "ทางออก 3",
        "lat": 13.757469865239802,
        "long": 100.53402549480565
      },
      {
        "id": 4,
        "exit_name": "ทางออก 4",
        "lat": 13.75737477325318,
        "long": 100.53423470710719
      },
      {
        "id": 5,
        "exit_name": "ทางออก 5",
        "lat": 13.75689019432725,
        "long": 100.53397319172748
      }
    ]
  },
  {
    "id": "N01",
    "name_th": "ราชเทวี",
    "name_en": "Ratchathewi",
    "type": 1,
    "type_name": "สายสีเขียวสุขุมวิท",
    "have_parking": 0,
    "lat": 13.75198798,
    "long": 100.5315729,
    "exit_doors": [
      {
        "id": 1,
        "exit_name": "ทางออก 1",
        "lat": 13.751552491759917,
        "long": 100.53136844582718
      },
      {
        "id": 2,
        "exit_name": "ทางออก 2",
        "lat": 13.75123884211518,
        "long": 100.53161721364494
      },
      {
        "id": 3,
        "exit_name": "ทางออก 3",
        "lat": 13.752499967148108,
        "long": 100.53153853034199
      },
      {
        "id": 4,
        "exit_name": "ทางออก 4",
        "lat": 13.752401929525185,
        "long": 100.5317949398395
      }
    ]
  },
  {
    "id": "E1",
    "name_th": "ชิดลม",
    "name_en": "Chit Lom",
    "type": 1,
    "type_name": "สายสีเขียวสุขุมวิท",
    "have_parking": 0,
    "lat": 13.74409601,
    "long": 100.5430565,
    "exit_doors": [
      {
        "id": 1,
        "exit_name": "ทางออก 1",
        "lat": 13.744354894280914,
        "long": 100.5422431083729
      },
      {
        "id": 2,
        "exit_name": "ทางออก 2",
        "lat": 13.7441518324544,
        "long": 100.54208992632539
      },
      {
        "id": 3,
        "exit_name": "ทางออก 3",
        "lat": 13.744136529285713,
        "long": 100.54347024344133
      },
      {
        "id": 4,
        "exit_name": "ทางออก 4",
        "lat": 13.743846140997004,
        "long": 100.54399842047255
      },
      {
        "id": 5,
        "exit_name": "ทางออก 5",
        "lat": 13.744005852142134,
        "long": 100.54403998295871
      },
      {
        "id": 6,
        "exit_name": "ทางออก 6",
        "lat": 13.744243442753204,
        "long": 100.5421667828954
      }
    ]
  },
  {
    "id": "E2",
    "name_th": "เพลินจิต",
    "name_en": "Phloen Chit",
    "type": 1,
    "type_name": "สายสีเขียวสุขุมวิท",
    "have_parking": 0,
    "lat": 13.74304693,
    "long": 100.5489771,
    "exit_doors": [
      {
        "id": 1,
        "exit_name": "ทางออก 1",
        "lat": 13.743213673850985,
        "long": 100.54877687958935
      },
      {
        "id": 2,
        "exit_name": "ทางออก 2",
        "lat": 13.742980396169676,
        "long": 100.54872810184085
      },
      {
        "id": 3,
        "exit_name": "ทางออก 3",
        "lat": 13.743051215563716,
        "long": 100.5495408122069
      },
      {
        "id": 4,
        "exit_name": "ทางออก 4",
        "lat": 13.74285025150007,
        "long": 100.54964032772163
      },
      {
        "id": 5,
        "exit_name": "ทางออก 5",
        "lat": 13.74303998209911,
        "long": 100.54843974241773
      }
    ]
  },
  {
    "id": "E3",
    "name_th": "นานา",
    "name_en": "Nana",
    "type": 1,
    "type_name": "สายสีเขียวสุขุมวิท",
    "have_parking": 0,
    "lat": 13.74052423,
    "long": 100.5554346,
    "exit_doors": [
      {
        "id": 1,
        "exit_name": "ทางออก 1",
        "lat": 13.740909756905902,
        "long": 100.5551094292769
      },
      {
        "id": 2,
        "exit_name": "ทางออก 2",
        "lat": 13.740766918325827,
        "long": 100.55493020421711
      },
      {
        "id": 3,
        "exit_name": "ทางออก 3",
        "lat": 13.740339556655368,
        "long": 100.55592280687958
      },
      {
        "id": 4,
        "exit_name": "ทางออก 4",
        "lat": 13.740165109847513,
        "long": 100.55571482603006
      }
    ]
  },
  {
    "id": "E4",
    "name_th": "อโศก",
    "name_en": "Asok",
    "type": 1,
    "type_name": "สายสีเขียวสุขุมวิท",
    "have_parking": 0,
    "lat": 13.73705742,
    "long": 100.5603046,
    "exit_doors": [
      {
        "id": 1,
        "exit_name": "ทางออก 1",
        "lat": 13.737404874299749,
        "long": 100.56006072884611
      },
      {
        "id": 2,
        "exit_name": "ทางออก 2",
        "lat": 13.73741668427117,
        "long": 100.55965377659278
      },
      {
        "id": 3,
        "exit_name": "ทางออก 3",
        "lat": 13.736992049784414,
        "long": 100.56082574806703
      },
      {
        "id": 4,
        "exit_name": "ทางออก 4",
        "lat": 13.736648607193692,
        "long": 100.56067647787393
      },
      {
        "id": 5,
        "exit_name": "ทางออก 5",
        "lat": 13.737749056146045,
        "long": 100.55961136357467
      },
      {
        "id": 6,
        "exit_name": "ทางออก 6",
        "lat": 13.736825516332406,
        "long": 100.56093451554442
      }
    ]
  },
  {
    "id": "E5",
    "name_th": "พร้อมพงษ์",
    "name_en": "Phrom Phong",
    "type": 1,
    "type_name": "สายสีเขียวสุขุมวิท",
    "have_parking": 0,
    "lat": 13.73042023,
    "long": 100.5697353,
    "exit_doors": [
      {
        "id": 1,
        "exit_name": "ทางออก 1",
        "lat": 13.730696450006384,
        "long": 100.56953820013725
      },
      {
        "id": 2,
        "exit_name": "ทางออก 2",
        "lat": 13.730489938974623,
        "long": 100.56945002709593
      },
      {
        "id": 3,
        "exit_name": "ทางออก 3",
        "lat": 13.730291390031637,
        "long": 100.57011071240714
      },
      {
        "id": 4,
        "exit_name": "ทางออก 4",
        "lat": 13.730119220326788,
        "long": 100.56995678208919
      },
      {
        "id": 5,
        "exit_name": "ทางออก 5",
        "lat": 13.731309937691456,
        "long": 100.56867640393537
      },
      {
        "id": 6,
        "exit_name": "ทางออก 6",
        "lat": 13.73116516257632,
        "long": 100.56847725434379
      }
    ]
  },
  {
    "id": "E6",
    "name_th": "ทองหล่อ",
    "name_en": "Thong Lo",
    "type": 1,
    "type_name": "สายสีเขียวสุขุมวิท",
    "have_parking": 0,
    "lat": 13.72428867,
    "long": 100.5784328,
    "exit_doors": [
      {
        "id": 1,
        "exit_name": "ทางออก 1",
        "lat": 13.724562787906134,
        "long": 100.57831559248429
      },
      {
        "id": 2,
        "exit_name": "ทางออก 2",
        "lat": 13.724359425775774,
        "long": 100.57817889687642
      },
      {
        "id": 3,
        "exit_name": "ทางออก 3",
        "lat": 13.723977542401983,
        "long": 100.57912836643632
      },
      {
        "id": 4,
        "exit_name": "ทางออก 4",
        "lat": 13.72388556443678,
        "long": 100.57886454880187
      }
    ]
  },
  {
    "id": "E7",
    "name_th": "เอกมัย",
    "name_en": "Ekkamai",
    "type": 1,
    "type_name": "สายสีเขียวสุขุมวิท",
    "have_parking": 0,
    "lat": 13.71952995,
    "long": 100.5850869,
    "exit_doors": [
      {
        "id": 1,
        "exit_name": "ทางออก 1",
        "lat": 13.719940626126288,
        "long": 100.584835679498
      },
      {
        "id": 2,
        "exit_name": "ทางออก 2",
        "lat": 13.719715718705773,
        "long": 100.58470962828989
      },
      {
        "id": 3,
        "exit_name": "ทางออก 3",
        "lat": 13.719220687890044,
        "long": 100.58581683714118
      },
      {
        "id": 4,
        "exit_name": "ทางออก 4",
        "lat": 13.719099464176969,
        "long": 100.58557190816347
      }
    ]
  },
  {
    "id": "E8",
    "name_th": "พระโขนง",
    "name_en": "Phra Khanong",
    "type": 1,
    "type_name": "สายสีเขียวสุขุมวิท",
    "have_parking": 0,
    "lat": 13.71516632,
    "long": 100.5912457,
    "exit_doors": [
      {
        "id": 1,
        "exit_name": "ทางออก 1",
        "lat": 13.715474873006565,
        "long": 100.59105741537756
      },
      {
        "id": 2,
        "exit_name": "ทางออก 2",
        "lat": 13.715235839591701,
        "long": 100.59099879984167
      },
      {
        "id": 3,
        "exit_name": "ทางออก 3",
        "lat": 13.71492794255718,
        "long": 100.59183759249896
      },
      {
        "id": 4,
        "exit_name": "ทางออก 4",
        "lat": 13.714798492402489,
        "long": 100.59159519896588
      }
    ]
  },
  {
    "id": "E9",
    "name_th": "อ่อนนุช",
    "name_en": "On Nut",
    "type": 1,
    "type_name": "สายสีเขียวสุขุมวิท",
    "have_parking": 0,
    "lat": 13.70564359,
    "long": 100.6009867,
    "exit_doors": [
      {
        "id": 1,
        "exit_name": "ทางออก 1",
        "lat": 13.7060318004712,
        "long": 100.60102558084938
      },
      {
        "id": 2,
        "exit_name": "ทางออก 2",
        "lat": 13.705702885483403,
        "long": 100.60079317237347
      },
      {
        "id": 3,
        "exit_name": "ทางออก 3",
        "lat": 13.705267518730487,
        "long": 100.60138167103796
      },
      {
        "id": 4,
        "exit_name": "ทางออก 4",
        "lat": 13.705022812322577,
        "long": 100.60119104226887
      }
    ]
  },
  {
    "id": "E10",
    "name_th": "บางจาก",
    "name_en": "Bang Chak",
    "type": 1,
    "type_name": "สายสีเขียวสุขุมวิท",
    "have_parking": 0,
    "lat": 13.69673434,
    "long": 100.6053209,
    "exit_doors": [
      {
        "id": 1,
        "exit_name": "ทางออก 1",
        "lat": 13.697260969890388,
        "long": 100.60532785396019
      },
      {
        "id": 2,
        "exit_name": "ทางออก 2",
        "lat": 13.69708077983222,
        "long": 100.60511219598881
      },
      {
        "id": 3,
        "exit_name": "ทางออก 3",
        "lat": 13.696493282393144,
        "long": 100.60569156569275
      },
      {
        "id": 4,
        "exit_name": "ทางออก 4",
        "lat": 13.696177016687782,
        "long": 100.6055995855222
      },
      {
        "id": 5,
        "exit_name": "ทางออก 5",
        "lat": 13.698030187754362,
        "long": 100.6047876964901
      }
    ]
  },
  {
    "id": "E11",
    "name_th": "ปุณณวิถี",
    "name_en": "Punnawithi",
    "type": 1,
    "type_name": "สายสีเขียวสุขุมวิท",
    "have_parking": 0,
    "lat": 13.68927878,
    "long": 100.6091055,
    "exit_doors": [
      {
        "id": 1,
        "exit_name": "ทางออก 1",
        "lat": 13.689500426014533,
        "long": 100.60906799757777
      },
      {
        "id": 2,
        "exit_name": "ทางออก 2",
        "lat": 13.689900448846847,
        "long": 100.60859726989659
      },
      {
        "id": 3,
        "exit_name": "ทางออก 3",
        "lat": 13.688751195760315,
        "long": 100.60940662647005
      },
      {
        "id": 4,
        "exit_name": "ทางออก 4",
        "lat": 13.689056100173856,
        "long": 100.60902508223403
      },
      {
        "id": 5,
        "exit_name": "ทางออก 5",
        "lat": 13.689290641778218,
        "long": 100.60914712274307
      },
      {
        "id": 6,
        "exit_name": "ทางออก 6",
        "lat": 13.688229990669754,
        "long": 100.60954945409584
      }
    ]
  },
  {
    "id": "E12",
    "name_th": "อุดมสุข",
    "name_en": "Udom Suk",
    "type": 1,
    "type_name": "สายสีเขียวสุขุมวิท",
    "have_parking": 0,
    "lat": 13.68010636,
    "long": 100.6096967,
    "exit_doors": [
      {
        "id": 1,
        "exit_name": "ทางออก 1",
        "lat": 13.680622353125898,
        "long": 100.6099004201075
      },
      {
        "id": 2,
        "exit_name": "ทางออก 2",
        "lat": 13.680601339176462,
        "long": 100.60963956629483
      },
      {
        "id": 3,
        "exit_name": "ทางออก 3",
        "lat": 13.679340826860823,
        "long": 100.60937484615808
      },
      {
        "id": 4,
        "exit_name": "ทางออก 4",
        "lat": 13.67944959958794,
        "long": 100.60916013041951
      },
      {
        "id": 5,
        "exit_name": "ทางออก 5",
        "lat": 13.680048389195253,
        "long": 100.60966854804552
      }
    ]
  },
  {
    "id": "E13",
    "name_th": "บางนา",
    "name_en": "Bang Na",
    "type": 1,
    "type_name": "สายสีเขียวสุขุมวิท",
    "have_parking": 0,
    "lat": 13.66813794,
    "long": 100.6046399,
    "exit_doors": [
      {
        "id": 1,
        "exit_name": "ทางออก 1",
        "lat": 13.668556302636246,
        "long": 100.60496666357544
      },
      {
        "id": 2,
        "exit_name": "ทางออก 2",
        "lat": 13.668788258429972,
        "long": 100.60480573103571
      },
      {
        "id": 3,
        "exit_name": "ทางออก 3",
        "lat": 13.667414764128356,
        "long": 100.60449995920438
      },
      {
        "id": 4,
        "exit_name": "ทางออก 4",
        "lat": 13.667586777121679,
        "long": 100.6043041579496
      },
      {
        "id": 5,
        "exit_name": "ทางออก 5",
        "lat": 13.667795277578836,
        "long": 100.60465820953708
      }
    ]
  },
  {
    "id": "E14",
    "name_th": "แบริ่ง",
    "name_en": "Bearing",
    "type": 1,
    "type_name": "สายสีเขียวสุขุมวิท",
    "have_parking": 0,
    "lat": 13.66124707,
    "long": 100.6016839,
    "exit_doors": [
      {
        "id": 1,
        "exit_name": "ทางออก 1",
        "lat": 13.661838048983832,
        "long": 100.60219689921244
      },
      {
        "id": 2,
        "exit_name": "ทางออก 2",
        "lat": 13.66204264503879,
        "long": 100.60203596667496
      },
      {
        "id": 3,
        "exit_name": "ทางออก 3",
        "lat": 13.660501002850998,
        "long": 100.60165241078234
      },
      {
        "id": 4,
        "exit_name": "ทางออก 4",
        "lat": 13.660686052579573,
        "long": 100.60147538499004
      },
      {
        "id": 5,
        "exit_name": "ทางออก 5",
        "lat": 13.661696004481241,
        "long": 100.60182943658
      }
    ]
  },
  {
    "id": "E15",
    "name_th": "สำโรง",
    "name_en": "Samrong",
    "type": 1,
    "type_name": "สายสีเขียวสุขุมวิท",
    "have_parking": 0,
    "lat": 13.646198,
    "long": 100.595649,
    "exit_doors": [
      {
        "id": 1,
        "exit_name": "ทางออก 1",
        "lat": 13.649597190067187,
        "long": 100.59696248970778
      },
      {
        "id": 2,
        "exit_name": "ทางออก 2",
        "lat": 13.646992940457595,
        "long": 100.59582198227605
      },
      {
        "id": 3,
        "exit_name": "ทางออก 3",
        "lat": 13.645688083783572,
        "long": 100.5956107349845
      },
      {
        "id": 4,
        "exit_name": "ทางออก 4",
        "lat": 13.64532317366828,
        "long": 100.59528484659
      },
      {
        "id": 5,
        "exit_name": "ทางออก 5",
        "lat": 13.64601519915357,
        "long": 100.59541091041457
      },
      {
        "id": 6,
        "exit_name": "ทางออก 6",
        "lat": 13.646204169974636,
        "long": 100.59580385403466
      }
    ]
  },
  {
    "id": "E16",
    "name_th": "ปู่เจ้า",
    "name_en": "Pu Chao",
    "type": 1,
    "type_name": "สายสีเขียวสุขุมวิท",
    "have_parking": 0,
    "lat": 13.63728361,
    "long": 100.5920074,
    "exit_doors": [
      {
        "id": 1,
        "exit_name": "ทางออก 1",
        "lat": 13.637998484572481,
        "long": 100.59242039885042
      },
      {
        "id": 2,
        "exit_name": "ทางออก 2",
        "lat": 13.637817326933424,
        "long": 100.59209048714253
      },
      {
        "id": 3,
        "exit_name": "ทางออก 3",
        "lat": 13.637005374093743,
        "long": 100.59202611412604
      },
      {
        "id": 4,
        "exit_name": "ทางออก 4",
        "lat": 13.636895897094508,
        "long": 100.59172168340123
      }
    ]
  },
  {
    "id": "E17",
    "name_th": "ช้างเอราวัณ",
    "name_en": "Chang Erawan",
    "type": 1,
    "type_name": "สายสีเขียวสุขุมวิท",
    "have_parking": 0,
    "lat": 13.6215499,
    "long": 100.5901569,
    "exit_doors": [
      {
        "id": 1,
        "exit_name": "ทางออก 1",
        "lat": 13.622239238956553,
        "long": 100.589999062375
      },
      {
        "id": 2,
        "exit_name": "ทางออก 2",
        "lat": 13.622441262579306,
        "long": 100.58967719729284
      },
      {
        "id": 3,
        "exit_name": "ทางออก 3",
        "lat": 13.621017969885704,
        "long": 100.59045503790671
      },
      {
        "id": 4,
        "exit_name": "ทางออก 4",
        "lat": 13.62075077571405,
        "long": 100.59028471763591
      },
      {
        "id": 5,
        "exit_name": "ทางออก 5",
        "lat": 13.621690515857313,
        "long": 100.59020693357387
      },
      {
        "id": 6,
        "exit_name": "ทางออก 6",
        "lat": 13.621921214322331,
        "long": 100.58985422308949
      }
    ]
  },
  {
    "id": "E18",
    "name_th": "โรงเรียนนายเรือ",
    "name_en": "Royal THai Naval Academy",
    "type": 1,
    "type_name": "สายสีเขียวสุขุมวิท",
    "have_parking": 0,
    "lat": 13.60848868,
    "long": 100.5949799,
    "exit_doors": [
      {
        "id": 1,
        "exit_name": "ทางออก 1",
        "lat": 13.608868049644562,
        "long": 100.59487655407834
      },
      {
        "id": 2,
        "exit_name": "ทางออก 2",
        "lat": 13.609174360772172,
        "long": 100.5945318902224
      },
      {
        "id": 3,
        "exit_name": "ทางออก 3",
        "lat": 13.608152453163347,
        "long": 100.59514075166632
      },
      {
        "id": 4,
        "exit_name": "ทางออก 4",
        "lat": 13.607996038347359,
        "long": 100.59493958599003
      }
    ]
  },
  {
    "id": "E19",
    "name_th": "ปากน้ำ",
    "name_en": "Pak Nam",
    "type": 1,
    "type_name": "สายสีเขียวสุขุมวิท",
    "have_parking": 0,
    "lat": 13.6020916,
    "long": 100.5971077,
    "exit_doors": [
      {
        "id": 1,
        "exit_name": "ทางออก 1",
        "lat": 13.60231247647241,
        "long": 100.5971773298072
      },
      {
        "id": 2,
        "exit_name": "ทางออก 2",
        "lat": 13.602463681093024,
        "long": 100.59688094570949
      },
      {
        "id": 3,
        "exit_name": "ทางออก 3",
        "lat": 13.601695925583169,
        "long": 100.5973422856617
      },
      {
        "id": 4,
        "exit_name": "ทางออก 4",
        "lat": 13.601087194065657,
        "long": 100.59724438503359
      },
      {
        "id": 5,
        "exit_name": "ทางออก 5",
        "lat": 13.601839309653231,
        "long": 100.5970445604615
      },
      {
        "id": 6,
        "exit_name": "ทางออก 6",
        "lat": 13.600379395067808,
        "long": 100.59728864148221
      }
    ]
  },
  {
    "id": "E20",
    "name_th": "ศรีนครินทร์",
    "name_en": "Srinagarindra",
    "type": 1,
    "type_name": "สายสีเขียวสุขุมวิท",
    "have_parking": 0,
    "lat": 13.59207899,
    "long": 100.6088738,
    "exit_doors": [
      {
        "id": 1,
        "exit_name": "ทางออก 1",
        "lat": 13.592933853929418,
        "long": 100.60867276409138
      },
      {
        "id": 2,
        "exit_name": "ทางออก 2",
        "lat": 13.592398098320015,
        "long": 100.6086513064193
      },
      {
        "id": 3,
        "exit_name": "ทางออก 3",
        "lat": 13.591669416604413,
        "long": 100.60934733965848
      },
      {
        "id": 4,
        "exit_name": "ทางออก 4",
        "lat": 13.591464759614311,
        "long": 100.60918104270154
      }
    ]
  },
  {
    "id": "E21",
    "name_th": "แพรกษา",
    "name_en": "Phwaek Sa",
    "type": 1,
    "type_name": "สายสีเขียวสุขุมวิท",
    "have_parking": 0,
    "lat": 13.58432943,
    "long": 100.6080227,
    "exit_doors": [
      {
        "id": 1,
        "exit_name": "ทางออก 1",
        "lat": 13.584697467978513,
        "long": 100.60820201204194
      },
      {
        "id": 2,
        "exit_name": "ทางออก 2",
        "lat": 13.584796540461648,
        "long": 100.60791233346599
      },
      {
        "id": 3,
        "exit_name": "ทางออก 3",
        "lat": 13.583967459013587,
        "long": 100.60794183776612
      },
      {
        "id": 4,
        "exit_name": "ทางออก 4",
        "lat": 13.58418646193905,
        "long": 100.60768166349031
      }
    ]
  },
  {
    "id": "E22",
    "name_th": "สายลวด",
    "name_en": "Sai Luat",
    "type": 1,
    "type_name": "สายสีเขียวสุขุมวิท",
    "have_parking": 0,
    "lat": 13.57770475,
    "long": 100.6053693,
    "exit_doors": [
      {
        "id": 1,
        "exit_name": "ทางออก 1",
        "lat": 13.578106913162616,
        "long": 100.6057461304188
      },
      {
        "id": 2,
        "exit_name": "ทางออก 2",
        "lat": 13.578297241849025,
        "long": 100.60546449847871
      },
      {
        "id": 3,
        "exit_name": "ทางออก 3",
        "lat": 13.577431636169512,
        "long": 100.60549400277505
      },
      {
        "id": 4,
        "exit_name": "ทางออก 4",
        "lat": 13.577402956405631,
        "long": 100.60513458677005
      }
    ]
  },
  {
    "id": "E23",
    "name_th": "เคหะฯ",
    "name_en": "Kheha",
    "type": 1,
    "type_name": "สายสีเขียวสุขุมวิท",
    "have_parking": 0,
    "lat": 13.56766347,
    "long": 100.6076721
  }
]